libnmap/__init__.py
libnmap/diff.py
libnmap/parser.py
libnmap/reportjson.py
libnmap/objects/__init__.py
libnmap/objects/cpe.py
libnmap/objects/host.py
libnmap/objects/os.py
libnmap/objects/report.py
libnmap/objects/service.py
natlas_libnmap-0.7.1.dist-info/LICENSE.txt
natlas_libnmap-0.7.1.dist-info/METADATA
natlas_libnmap-0.7.1.dist-info/WHEEL
natlas_libnmap-0.7.1.dist-info/top_level.txt
natlas_libnmap-0.7.1.dist-info/RECORD
