Metadata-Version: 2.1
Name: natlas-libnmap
Version: 0.7.1
Summary: Python NMAP library enabling you to start async nmap tasks, parse and compare/diff scan results
Home-page: http://pypi.python.org/pypi/natlas-libnmap/
Author: 0xdade
Author-email: dade@actualcrimes.org
License: Creative Common "Attribution" license (CC-BY) v3
Platform: UNKNOWN
Classifier: Development Status :: 5 - Production/Stable
Classifier: Environment :: Console
Classifier: Programming Language :: Python :: 3
Classifier: Programming Language :: Python :: 3.6
Classifier: Topic :: System :: Networking
Requires-Dist: defusedxml
